audiencelab_python_sdk/__init__.py
audiencelab_python_sdk/client.py
audiencelab_python_sdk/sdk_version.py
audiencelab_python_sdk/api/__init__.py
audiencelab_python_sdk/api/app_event.py
audiencelab_python_sdk/api/fetch_token.py
audiencelab_python_sdk/api/register_user.py
audiencelab_python_sdk/api/update_cumulative_values.py
audiencelab_python_sdk/models/__init__.py
audiencelab_python_sdk/models/ad_data.py
audiencelab_python_sdk/models/purchase_data.py
audiencelab_python_sdk/models/retention_data.py
audiencelab_python_sdk/models/userdata.py
audiencelab_python_sdk-1.0.4.dist-info/licenses/LICENSE.md
audiencelab_python_sdk-1.0.4.dist-info/METADATA
audiencelab_python_sdk-1.0.4.dist-info/WHEEL
audiencelab_python_sdk-1.0.4.dist-info/top_level.txt
audiencelab_python_sdk-1.0.4.dist-info/RECORD
