Metadata-Version: 2.4
Name: audiencelab_python_sdk
Version: 1.0.4
Summary: Python SDK for AudienceLab services
Home-page: https://github.com/Geeklab-Ltd/audiencelab_python_sdk
Author: Nathan Nylund
Author-email: nathan@geeklab.app
Classifier: Programming Language :: Python :: 3
Requires-Python: >=3.6
License-File: LICENSE.md
Requires-Dist: requests>=2.0.0
Dynamic: author
Dynamic: author-email
Dynamic: classifier
Dynamic: description
Dynamic: description-content-type
Dynamic: home-page
Dynamic: license-file
Dynamic: requires-dist
Dynamic: requires-python
Dynamic: summary
